Metadata-Version: 2.1
Name: altimate-django
Version: 0.1.5
Summary: A Django extension to check for various data issues
Home-page: UNKNOWN
Author: Altimate Inc.
Author-email: info@altimate.ai
License: UNKNOWN
Platform: UNKNOWN
Classifier: Development Status :: 3 - Alpha
Classifier: Environment :: Web Environment
Classifier: Framework :: Django
Classifier: Intended Audience :: Developers
Classifier: License :: OSI Approved :: MIT License
Classifier: Operating System :: OS Independent
Classifier: Programming Language :: Python
Classifier: Programming Language :: Python :: 3
Classifier: Programming Language :: Python :: 3.6
Classifier: Programming Language :: Python :: 3.7
Classifier: Programming Language :: Python :: 3.8
Classifier: Programming Language :: Python :: 3.9
Classifier: Programming Language :: Python :: 3.10
License-File: LICENSE
Requires-Dist: Django (>=2.0)
Requires-Dist: tabulate (>=0.9.0)
Requires-Dist: termcolor (>=1.1.0)
